pulsar_asyncio/__init__.py
pulsar_asyncio/version.py
pulsar_asyncio_client-0.1.0.dist-info/METADATA
pulsar_asyncio_client-0.1.0.dist-info/WHEEL
pulsar_asyncio_client-0.1.0.dist-info/entry_points.txt
pulsar_asyncio_client-0.1.0.dist-info/licenses/LICENSE
pulsar_asyncio_client-0.1.0.dist-info/RECORD
