Metadata-Version: 2.1
Name: pulsar-asyncio-client
Version: 0.1.0
Summary: Wrapper for pulsar-client that publishes messages asynchronously and handles consumed messages in an asyncio event loop
Author-Email: Mark Parncutt <me@markparncutt.com>
License: MIT
Requires-Python: >=3.8
Requires-Dist: pulsar-client>=3.5.0
